yttext/__init__.py
yttext/scrape.py
yttext-0.0.2.dist-info/METADATA
yttext-0.0.2.dist-info/WHEEL
yttext-0.0.2.dist-info/top_level.txt
yttext-0.0.2.dist-info/RECORD
