Metadata-Version: 2.1
Name: yttext
Version: 0.0.2
Summary: A Python package for scraping subtitles from youtube videos.
Home-page: https://github.com/lukemvc/yttext
Requires-Dist: requests
